eth_portal/__init__.py
eth_portal/portal_encode.py
eth_portal/py.typed
eth_portal/ssz_sedes.py
eth_portal/trin.py
eth_portal/web3_decode.py
eth_portal/bridge/__init__.py
eth_portal/bridge/__main__.py
eth_portal/bridge/handle.py
eth_portal/bridge/history.py
eth_portal/bridge/inject.py
eth_portal/bridge/insert.py
eth_portal/bridge/run.py
eth_portal-0.2.1.dist-info/LICENSE
eth_portal-0.2.1.dist-info/METADATA
eth_portal-0.2.1.dist-info/WHEEL
eth_portal-0.2.1.dist-info/top_level.txt
eth_portal-0.2.1.dist-info/RECORD
